p3_test_driver/__init__.py
p3_test_driver/application_status_tree.py
p3_test_driver/hadoop_util.py
p3_test_driver/json_util.py
p3_test_driver/optimizer.py
p3_test_driver/p3_metrics.py
p3_test_driver/p3_plugin_manager.py
p3_test_driver/p3_storage.py
p3_test_driver/p3_test.py
p3_test_driver/p3_test_driver.py
p3_test_driver/p3_test_hadoop.py
p3_test_driver/p3_util.py
p3_test_driver/system_command.py
p3_test_driver/test_application_status_tree.py
p3_test_driver/plugins/p3_storage_ecs.py
p3_test_driver/plugins/p3_storage_isilon.py
p3_test_driver/plugins/p3_test_dummy.py
p3_test_driver/plugins/p3_test_openmessaging_benchmark.py
p3_test_driver/plugins/p3_test_simple.py
p3_test_driver-2.0.3.dist-info/LICENSE
p3_test_driver-2.0.3.dist-info/METADATA
p3_test_driver-2.0.3.dist-info/WHEEL
p3_test_driver-2.0.3.dist-info/entry_points.txt
p3_test_driver-2.0.3.dist-info/top_level.txt
p3_test_driver-2.0.3.dist-info/RECORD
