Metadata-Version: 2.1
Name: p3-test-driver
Version: 2.0.3
Summary: P3 Test Driver is designed to run a variety of benchmarks using an easily expandable plug-in system.
Home-page: http://github.com/pravega/p3_test_driver
Author: Claudio Fahey
Author-email: claudio.fahey@dell.com
License: UNKNOWN
Platform: UNKNOWN
Classifier: License :: OSI Approved :: Apache Software License
Classifier: Operating System :: OS Independent
Classifier: Programming Language :: Python :: 3
Requires-Dist: requests
Requires-Dist: six
Requires-Dist: PyYaml
Requires-Dist: yapsy
